{
  "global_description": "Ad creative 'creative_500242'. Contains 6 text/button regions: Dinner in minutes Late-night deals available; SnapMeal; Start now; 30%; SALE. Contains 11 visual background elements. Text layout: 3 at bottom, 3 at top.",
  "elements": [
    {
      "id": 1,
      "label": "VISUAL ELEMENT",
      "text": "",
      "coords": [
        1.88,
        78.12,
        359.38,
        271.25
      ],
      "area_percentage": 29.97
    },
    {
      "id": 2,
      "label": "VISUAL ELEMENT",
      "text": "",
      "coords": [
        1.88,
        78.75,
        359.38,
        250.62
      ],
      "area_percentage": 26.67
    },
    {
      "id": 3,
      "label": "VISUAL ELEMENT",
      "text": "",
      "coords": [
        0.0,
        0.0,
        359.38,
        156.25
      ],
      "area_percentage": 24.37
    },
    {
      "id": 4,
      "label": "VISUAL ELEMENT",
      "text": "",
      "coords": [
        1.88,
        78.12,
        359.38,
        228.75
      ],
      "area_percentage": 23.37
    },
    {
      "id": 5,
      "label": "VISUAL ELEMENT",
      "text": "",
      "coords": [
        0.0,
        0.0,
        359.38,
        115.62
      ],
      "area_percentage": 18.03
    },
    {
      "id": 6,
      "label": "VISUAL ELEMENT",
      "text": "",
      "coords": [
        60.62,
        32.5,
        335.0,
        85.0
      ],
      "area_percentage": 6.25
    },
    {
      "id": 7,
      "label": "VISUAL ELEMENT",
      "text": "",
      "coords": [
        54.38,
        180.0,
        118.12,
        293.75
      ],
      "area_percentage": 3.15
    },
    {
      "id": 8,
      "label": "VISUAL ELEMENT",
      "text": "",
      "coords": [
        133.75,
        199.38,
        196.88,
        312.5
      ],
      "area_percentage": 3.1
    },
    {
      "id": 9,
      "label": "VISUAL ELEMENT",
      "text": "",
      "coords": [
        213.12,
        180.62,
        276.25,
        293.75
      ],
      "area_percentage": 3.1
    },
    {
      "id": 10,
      "label": "VISUAL ELEMENT",
      "text": "",
      "coords": [
        0.0,
        116.25,
        31.88,
        190.0
      ],
      "area_percentage": 1.02
    },
    {
      "id": 11,
      "label": "VISUAL ELEMENT",
      "text": "",
      "coords": [
        43.12,
        353.12,
        78.75,
        389.38
      ],
      "area_percentage": 0.56
    },
    {
      "id": 12,
      "label": "TEXT/BUTTON: Dinner in minutes Late-night deals available",
      "text": "Dinner in minutes Late-night deals available",
      "coords": [
        66,
        409,
        292,
        500
      ],
      "area_percentage": 8.93
    },
    {
      "id": 13,
      "label": "TEXT/BUTTON: SnapMeal",
      "text": "SnapMeal",
      "coords": [
        26,
        48,
        136,
        72
      ],
      "area_percentage": 1.15
    },
    {
      "id": 14,
      "label": "TEXT/BUTTON: Start now",
      "text": "Start now",
      "coords": [
        127,
        561,
        233,
        581
      ],
      "area_percentage": 0.92
    },
    {
      "id": 15,
      "label": "TEXT/BUTTON: 30%",
      "text": "30%",
      "coords": [
        34,
        532,
        90,
        556
      ],
      "area_percentage": 0.58
    },
    {
      "id": 16,
      "label": "TEXT/BUTTON: SALE",
      "text": "SALE",
      "coords": [
        271,
        47,
        321,
        67
      ],
      "area_percentage": 0.43
    },
    {
      "id": 17,
      "label": "TEXT/BUTTON: UGC",
      "text": "UGC",
      "coords": [
        29,
        113,
        61,
        127
      ],
      "area_percentage": 0.19
    }
  ]
}