{
  "global_description": "Ad creative 'creative_500639'. Contains 3 text/button regions: Fast food, fast Late-night deals available €29.99 Try for free; PlateSprint; SALE. Contains 4 visual background elements. Text layout: 1 at bottom, 2 at top.",
  "elements": [
    {
      "id": 1,
      "label": "VISUAL ELEMENT",
      "text": "",
      "coords": [
        48.44,
        89.38,
        105.31,
        146.25
      ],
      "area_percentage": 3.16
    },
    {
      "id": 2,
      "label": "VISUAL ELEMENT",
      "text": "",
      "coords": [
        118.44,
        99.38,
        175.31,
        155.94
      ],
      "area_percentage": 3.14
    },
    {
      "id": 3,
      "label": "VISUAL ELEMENT",
      "text": "",
      "coords": [
        127.19,
        107.81,
        166.56,
        139.69
      ],
      "area_percentage": 1.23
    },
    {
      "id": 4,
      "label": "VISUAL ELEMENT",
      "text": "",
      "coords": [
        38.75,
        169.38,
        70.31,
        199.69
      ],
      "area_percentage": 0.93
    },
    {
      "id": 5,
      "label": "TEXT/BUTTON: Fast food, fast Late-night deals available €29.99 Try for free",
      "text": "Fast food, fast Late-night deals available €29.99 Try for free",
      "coords": [
        22,
        202,
        275,
        299
      ],
      "area_percentage": 23.97
    },
    {
      "id": 6,
      "label": "TEXT/BUTTON: PlateSprint",
      "text": "PlateSprint",
      "coords": [
        25,
        20,
        112,
        36
      ],
      "area_percentage": 1.36
    },
    {
      "id": 7,
      "label": "TEXT/BUTTON: SALE",
      "text": "SALE",
      "coords": [
        241,
        23,
        287,
        41
      ],
      "area_percentage": 0.81
    }
  ]
}