{
  "global_description": "Ad creative 'creative_500306'. Contains 2 text/button regions: Book your next trip 30% Book now; HorizonHop. Contains 10 visual background elements. Text layout: 1 at bottom, 1 at top.",
  "elements": [
    {
      "id": 1,
      "label": "VISUAL ELEMENT",
      "text": "",
      "coords": [
        15.94,
        63.44,
        305.0,
        235.62
      ],
      "area_percentage": 48.6
    },
    {
      "id": 2,
      "label": "VISUAL ELEMENT",
      "text": "",
      "coords": [
        0.62,
        0.0,
        319.69,
        57.5
      ],
      "area_percentage": 17.92
    },
    {
      "id": 3,
      "label": "VISUAL ELEMENT",
      "text": "",
      "coords": [
        54.06,
        76.56,
        246.88,
        164.06
      ],
      "area_percentage": 16.48
    },
    {
      "id": 4,
      "label": "VISUAL ELEMENT",
      "text": "",
      "coords": [
        58.75,
        104.06,
        249.38,
        166.56
      ],
      "area_percentage": 11.64
    },
    {
      "id": 5,
      "label": "VISUAL ELEMENT",
      "text": "",
      "coords": [
        100.62,
        107.81,
        249.69,
        166.56
      ],
      "area_percentage": 8.55
    },
    {
      "id": 6,
      "label": "VISUAL ELEMENT",
      "text": "",
      "coords": [
        54.38,
        76.56,
        159.06,
        149.69
      ],
      "area_percentage": 7.48
    },
    {
      "id": 7,
      "label": "VISUAL ELEMENT",
      "text": "",
      "coords": [
        127.81,
        108.12,
        249.69,
        166.56
      ],
      "area_percentage": 6.96
    },
    {
      "id": 8,
      "label": "VISUAL ELEMENT",
      "text": "",
      "coords": [
        57.5,
        79.38,
        155.94,
        147.19
      ],
      "area_percentage": 6.52
    },
    {
      "id": 9,
      "label": "VISUAL ELEMENT",
      "text": "",
      "coords": [
        38.12,
        169.38,
        70.62,
        201.56
      ],
      "area_percentage": 1.02
    },
    {
      "id": 10,
      "label": "VISUAL ELEMENT",
      "text": "",
      "coords": [
        39.38,
        170.31,
        69.69,
        200.62
      ],
      "area_percentage": 0.9
    },
    {
      "id": 11,
      "label": "TEXT/BUTTON: Book your next trip 30% Book now",
      "text": "Book your next trip 30% Book now",
      "coords": [
        30,
        206,
        278,
        299
      ],
      "area_percentage": 22.52
    },
    {
      "id": 12,
      "label": "TEXT/BUTTON: HorizonHop",
      "text": "HorizonHop",
      "coords": [
        24,
        19,
        113,
        37
      ],
      "area_percentage": 1.56
    }
  ]
}