{
  "global_description": "Ad creative 'creative_501117'. Contains 3 text/button regions: RouteBloon; Fly smarter Hotels flights in one tap; Get offer. Contains 7 visual background elements. Text layout: 1 at top, 2 at bottom.",
  "elements": [
    {
      "id": 1,
      "label": "VISUAL ELEMENT",
      "text": "",
      "coords": [
        0.0,
        0.0,
        360.0,
        639.38
      ],
      "area_percentage": 99.9
    },
    {
      "id": 2,
      "label": "VISUAL ELEMENT",
      "text": "",
      "coords": [
        1.25,
        103.75,
        359.38,
        229.38
      ],
      "area_percentage": 19.53
    },
    {
      "id": 3,
      "label": "VISUAL ELEMENT",
      "text": "",
      "coords": [
        68.12,
        178.12,
        280.0,
        332.5
      ],
      "area_percentage": 14.2
    },
    {
      "id": 4,
      "label": "VISUAL ELEMENT",
      "text": "",
      "coords": [
        62.5,
        153.75,
        179.38,
        299.38
      ],
      "area_percentage": 7.39
    },
    {
      "id": 5,
      "label": "VISUAL ELEMENT",
      "text": "",
      "coords": [
        143.75,
        218.12,
        280.0,
        331.25
      ],
      "area_percentage": 6.69
    },
    {
      "id": 6,
      "label": "VISUAL ELEMENT",
      "text": "",
      "coords": [
        43.75,
        353.12,
        78.75,
        389.38
      ],
      "area_percentage": 0.55
    },
    {
      "id": 7,
      "label": "VISUAL ELEMENT",
      "text": "",
      "coords": [
        200.62,
        195.62,
        241.25,
        216.88
      ],
      "area_percentage": 0.37
    },
    {
      "id": 8,
      "label": "TEXT/BUTTON: RouteBloon",
      "text": "RouteBloon",
      "coords": [
        28,
        40,
        360,
        96
      ],
      "area_percentage": 8.07
    },
    {
      "id": 9,
      "label": "TEXT/BUTTON: Fly smarter Hotels flights in one tap",
      "text": "Fly smarter Hotels flights in one tap",
      "coords": [
        65,
        411,
        295,
        467
      ],
      "area_percentage": 5.59
    },
    {
      "id": 10,
      "label": "TEXT/BUTTON: Get offer",
      "text": "Get offer",
      "coords": [
        133,
        561,
        227,
        581
      ],
      "area_percentage": 0.82
    }
  ]
}