{
  "global_description": "Ad creative 'creative_501126'. Contains 4 text/button regions: destinations await Flexible booking options €29.99 Install now; DriftPass UGC; Dream; DTe[ ntintzu;. Contains 5 visual background elements. Text layout: 2 at bottom, 2 at top.",
  "elements": [
    {
      "id": 1,
      "label": "VISUAL ELEMENT",
      "text": "",
      "coords": [
        145.62,
        217.5,
        279.38,
        361.25
      ],
      "area_percentage": 8.35
    },
    {
      "id": 2,
      "label": "VISUAL ELEMENT",
      "text": "",
      "coords": [
        145.62,
        218.12,
        278.75,
        332.5
      ],
      "area_percentage": 6.61
    },
    {
      "id": 3,
      "label": "VISUAL ELEMENT",
      "text": "",
      "coords": [
        11.88,
        161.25,
        128.12,
        189.38
      ],
      "area_percentage": 1.42
    },
    {
      "id": 4,
      "label": "VISUAL ELEMENT",
      "text": "",
      "coords": [
        20.62,
        107.5,
        73.12,
        159.38
      ],
      "area_percentage": 1.18
    },
    {
      "id": 5,
      "label": "VISUAL ELEMENT",
      "text": "",
      "coords": [
        43.12,
        351.88,
        80.0,
        388.75
      ],
      "area_percentage": 0.59
    },
    {
      "id": 6,
      "label": "TEXT/BUTTON: destinations await Flexible booking options €29.99 Install now",
      "text": "destinations await Flexible booking options €29.99 Install now",
      "coords": [
        24,
        443,
        288,
        581
      ],
      "area_percentage": 15.81
    },
    {
      "id": 7,
      "label": "TEXT/BUTTON: DriftPass UGC",
      "text": "DriftPass UGC",
      "coords": [
        28,
        40,
        302,
        127
      ],
      "area_percentage": 10.35
    },
    {
      "id": 8,
      "label": "TEXT/BUTTON: Dream",
      "text": "Dream",
      "coords": [
        122,
        410,
        239,
        446
      ],
      "area_percentage": 1.83
    },
    {
      "id": 9,
      "label": "TEXT/BUTTON: DTe[ ntintzu;",
      "text": "DTe[ ntintzu;",
      "coords": [
        138,
        160,
        210,
        168
      ],
      "area_percentage": 0.25
    }
  ]
}