{
  "global_description": "Ad creative 'creative_500988'. Contains 2 text/button regions: Your money, clearer Built Claim reward; NovaPay. Contains 3 visual background elements. Text layout: 1 at bottom, 1 at top.",
  "elements": [
    {
      "id": 1,
      "label": "VISUAL ELEMENT",
      "text": "",
      "coords": [
        0.0,
        0.0,
        319.69,
        57.19
      ],
      "area_percentage": 17.85
    },
    {
      "id": 2,
      "label": "VISUAL ELEMENT",
      "text": "",
      "coords": [
        59.06,
        99.06,
        249.69,
        166.88
      ],
      "area_percentage": 12.63
    },
    {
      "id": 3,
      "label": "VISUAL ELEMENT",
      "text": "",
      "coords": [
        54.06,
        76.25,
        159.38,
        150.0
      ],
      "area_percentage": 7.59
    },
    {
      "id": 4,
      "label": "TEXT/BUTTON: Your money, clearer Built Claim reward",
      "text": "Your money, clearer Built Claim reward",
      "coords": [
        63,
        201,
        258,
        299
      ],
      "area_percentage": 18.66
    },
    {
      "id": 5,
      "label": "TEXT/BUTTON: NovaPay",
      "text": "NovaPay",
      "coords": [
        24,
        19,
        93,
        37
      ],
      "area_percentage": 1.21
    }
  ]
}