[
  {
    "id": 1,
    "label": "TEXT: RouteBloom SALE Book your next trip Special fares today",
    "text": "RouteBloom SALE Book your next trip Special fares today",
    "coords": [
      0.0,
      0.0,
      360.0,
      639.13
    ],
    "area_percentage": 99.86
  },
  {
    "id": 2,
    "label": "VISUAL ELEMENT",
    "text": "",
    "coords": [
      144.35,
      215.65,
      280.0,
      332.17
    ],
    "area_percentage": 6.86
  },
  {
    "id": 3,
    "label": "VISUAL ELEMENT",
    "text": "",
    "coords": [
      81.74,
      538.26,
      261.74,
      601.74
    ],
    "area_percentage": 4.96
  },
  {
    "id": 4,
    "label": "TEXT: €29.99 Order now",
    "text": "€29.99 Order now",
    "coords": [
      99.13,
      550.43,
      260.87,
      601.74
    ],
    "area_percentage": 3.6
  },
  {
    "id": 5,
    "label": "VISUAL ELEMENT",
    "text": "",
    "coords": [
      271.3,
      31.3,
      333.91,
      83.48
    ],
    "area_percentage": 1.42
  },
  {
    "id": 6,
    "label": "VISUAL ELEMENT",
    "text": "",
    "coords": [
      106.96,
      366.96,
      142.61,
      402.61
    ],
    "area_percentage": 0.55
  },
  {
    "id": 7,
    "label": "VISUAL ELEMENT",
    "text": "",
    "coords": [
      172.17,
      353.04,
      206.96,
      388.7
    ],
    "area_percentage": 0.54
  },
  {
    "id": 8,
    "label": "VISUAL ELEMENT",
    "text": "",
    "coords": [
      43.48,
      353.91,
      78.26,
      388.7
    ],
    "area_percentage": 0.53
  },
  {
    "id": 9,
    "label": "VISUAL ELEMENT",
    "text": "",
    "coords": [
      143.48,
      45.22,
      163.48,
      70.43
    ],
    "area_percentage": 0.22
  },
  {
    "id": 10,
    "label": "VISUAL ELEMENT",
    "text": "",
    "coords": [
      53.04,
      414.78,
      71.3,
      436.52
    ],
    "area_percentage": 0.17
  },
  {
    "id": 11,
    "label": "VISUAL ELEMENT",
    "text": "",
    "coords": [
      180.87,
      51.3,
      200.0,
      70.43
    ],
    "area_percentage": 0.16
  },
  {
    "id": 12,
    "label": "VISUAL ELEMENT",
    "text": "",
    "coords": [
      254.78,
      420.87,
      272.17,
      436.52
    ],
    "area_percentage": 0.12
  }
]