[
  {
    "id": 1,
    "label": "TEXT: Hungry? We got you Fresh favorites nearby 30% Order now",
    "text": "Hungry? We got you Fresh favorites nearby 30% Order now",
    "coords": [
      0.0,
      0.0,
      320.0,
      479.35
    ],
    "area_percentage": 99.86
  },
  {
    "id": 2,
    "label": "VISUAL ELEMENT",
    "text": "",
    "coords": [
      88.04,
      373.7,
      232.83,
      450.65
    ],
    "area_percentage": 7.25
  },
  {
    "id": 3,
    "label": "VISUAL ELEMENT",
    "text": "",
    "coords": [
      88.04,
      412.17,
      232.83,
      450.65
    ],
    "area_percentage": 3.63
  },
  {
    "id": 4,
    "label": "TEXT: BiteRush",
    "text": "BiteRush",
    "coords": [
      15.65,
      23.48,
      142.17,
      62.61
    ],
    "area_percentage": 3.22
  },
  {
    "id": 5,
    "label": "VISUAL ELEMENT",
    "text": "",
    "coords": [
      118.7,
      148.7,
      174.78,
      233.48
    ],
    "area_percentage": 3.1
  },
  {
    "id": 6,
    "label": "VISUAL ELEMENT",
    "text": "",
    "coords": [
      48.91,
      135.0,
      104.35,
      219.13
    ],
    "area_percentage": 3.04
  },
  {
    "id": 7,
    "label": "TEXT: SALE",
    "text": "SALE",
    "coords": [
      230.22,
      23.48,
      297.39,
      62.61
    ],
    "area_percentage": 1.71
  },
  {
    "id": 8,
    "label": "VISUAL ELEMENT",
    "text": "",
    "coords": [
      100.43,
      318.26,
      115.43,
      338.48
    ],
    "area_percentage": 0.2
  },
  {
    "id": 9,
    "label": "VISUAL ELEMENT",
    "text": "",
    "coords": [
      204.78,
      318.26,
      219.78,
      333.26
    ],
    "area_percentage": 0.15
  }
]