{
  "global_description": "Ad creative 'creative_500624'. Contains 3 text/button regions: SwiftStack; Save with confidence No hidden fees; Claim reward. Contains 8 visual background elements. Text layout: 1 at top, 2 at bottom.",
  "elements": [
    {
      "id": 1,
      "label": "VISUAL ELEMENT",
      "text": "",
      "coords": [
        1.25,
        92.5,
        359.38,
        291.25
      ],
      "area_percentage": 30.89
    },
    {
      "id": 2,
      "label": "VISUAL ELEMENT",
      "text": "",
      "coords": [
        1.88,
        91.25,
        359.38,
        229.38
      ],
      "area_percentage": 21.43
    },
    {
      "id": 3,
      "label": "VISUAL ELEMENT",
      "text": "",
      "coords": [
        68.12,
        177.5,
        280.0,
        331.88
      ],
      "area_percentage": 14.2
    },
    {
      "id": 4,
      "label": "VISUAL ELEMENT",
      "text": "",
      "coords": [
        61.88,
        155.0,
        178.75,
        298.75
      ],
      "area_percentage": 7.29
    },
    {
      "id": 5,
      "label": "VISUAL ELEMENT",
      "text": "",
      "coords": [
        144.38,
        218.75,
        278.75,
        330.62
      ],
      "area_percentage": 6.52
    },
    {
      "id": 6,
      "label": "VISUAL ELEMENT",
      "text": "",
      "coords": [
        0.0,
        116.25,
        48.75,
        189.38
      ],
      "area_percentage": 1.55
    },
    {
      "id": 7,
      "label": "VISUAL ELEMENT",
      "text": "",
      "coords": [
        43.12,
        353.75,
        78.75,
        389.38
      ],
      "area_percentage": 0.55
    },
    {
      "id": 8,
      "label": "VISUAL ELEMENT",
      "text": "",
      "coords": [
        200.0,
        195.62,
        241.25,
        216.88
      ],
      "area_percentage": 0.38
    },
    {
      "id": 9,
      "label": "TEXT/BUTTON: SwiftStack",
      "text": "SwiftStack",
      "coords": [
        25,
        37,
        351,
        97
      ],
      "area_percentage": 8.49
    },
    {
      "id": 10,
      "label": "TEXT/BUTTON: Save with confidence No hidden fees",
      "text": "Save with confidence No hidden fees",
      "coords": [
        85,
        409,
        277,
        497
      ],
      "area_percentage": 7.33
    },
    {
      "id": 11,
      "label": "TEXT/BUTTON: Claim reward",
      "text": "Claim reward",
      "coords": [
        111,
        561,
        247,
        581
      ],
      "area_percentage": 1.18
    }
  ]
}